LICENSE
README.md
setup.py
python3_server.egg-info/PKG-INFO
python3_server.egg-info/SOURCES.txt
python3_server.egg-info/dependency_links.txt
python3_server.egg-info/requires.txt
python3_server.egg-info/top_level.txt
server/__init__.py
server/server.py