Metadata-Version: 2.1
Name: python3-server
Version: 0.0.2
Summary: used to get or do something on self which is serer for example linux or windwos or other os.
Home-page: https://gitee.com/devops_dev/server
Author: redrose2100
Author-email: hitredrose@163.com
Maintainer: redrose2100
Maintainer-email: hitredrose@163.com
License: MIT
Project-URL: Documentation, https://gitee.com/devops_dev/server/README.md
Classifier: Development Status :: 4 - Beta
Classifier: Intended Audience :: Developers
Classifier: Topic :: System :: Logging
Classifier: License :: OSI Approved :: MIT License
Classifier: Programming Language :: Python :: 3
Classifier: Programming Language :: Python :: 3.3
Classifier: Programming Language :: Python :: 3.4
Classifier: Programming Language :: Python :: 3.5
Classifier: Programming Language :: Python :: 3.6
Classifier: Programming Language :: Python :: 3.7
Classifier: Programming Language :: Python :: 3.8
Classifier: Programming Language :: Python :: 3.9
Classifier: Programming Language :: Python :: 3.10
Classifier: Programming Language :: Python :: 3.11
Classifier: Programming Language :: Python :: 3.12
License-File: LICENSE
Requires-Dist: python3-log
